logistic_regression_model/VERSION
logistic_regression_model/__init__.py
logistic_regression_model/main.py
logistic_regression_model/data_prep/__init__.py
logistic_regression_model/data_prep/data_processing.py
logistic_regression_model/data_prep/validation.py
logistic_regression_model/evaluation/__init__.py
logistic_regression_model/evaluation/model_evaluation.py
logistic_regression_model/input_data/Sports_News_03_06_2021.csv
logistic_regression_model/input_data/Sports_News_09_09_2021.csv
logistic_regression_model/modelling_evaluation/__init__.py
logistic_regression_model/modelling_evaluation/build_models.py
logistic_regression_model/modelling_evaluation/modelling.py
logistic_regression_model/modelling_evaluation/predict.py
logistic_regression_model/parameters/__init__.py
logistic_regression_model/parameters/project_parameters.py
logistic_regression_model/saved_models/count_vector.pkl
logistic_regression_model/saved_models/final_model.joblib
logistic_regression_model/saved_models/tfidf.pkl
tid_logistic_regression_model-1.0.10.dist-info/METADATA
tid_logistic_regression_model-1.0.10.dist-info/WHEEL
tid_logistic_regression_model-1.0.10.dist-info/top_level.txt
tid_logistic_regression_model-1.0.10.dist-info/RECORD
